tabulux/__init__.py
tabulux-1.2.0.dist-info/LICENSE
tabulux-1.2.0.dist-info/METADATA
tabulux-1.2.0.dist-info/WHEEL
tabulux-1.2.0.dist-info/top_level.txt
tabulux-1.2.0.dist-info/RECORD
