Metadata-Version: 2.1
Name: tabulux
Version: 1.2.0
Summary: A package to form and retrieve tabular data
Home-page: https://github.com/John-pix/Tabulux-Python
Author: John-Anchery
Author-email: JohnPix005@gmail.com
License: UNKNOWN
Platform: UNKNOWN
Classifier: Programming Language :: Python :: 3
Classifier: License :: OSI Approved :: MIT License
Classifier: Operating System :: OS Independent
Requires-Python: >=3.6
